waifu_python/__init__.py
waifu_python/__main__.py
waifu_python/AI/__init__.py
waifu_python/AI/aibooru.py
waifu_python/API/__init__.py
waifu_python/API/api.py
waifu_python/API/base.py
waifu_python/API/pixiv_auth.py
waifu_python/Anilist/Anilist.py
waifu_python/Anilist/__init__.py
waifu_python/Boards/Danbooru.py
waifu_python/Boards/Gelborru.py
waifu_python/Boards/Hijiribe.py
waifu_python/Boards/Safeborru.py
waifu_python/Boards/Tbib.py
waifu_python/Boards/__init__.py
waifu_python/CLI/__init__.py
waifu_python/CLI/commands.py
waifu_python/CLI/parser.py
waifu_python/Client/Client.py
waifu_python/Client/__init__.py
waifu_python/Galleries/Kemono.py
waifu_python/Galleries/Konachan.py
waifu_python/Galleries/NekosBest.py
waifu_python/Galleries/NsfwBot.py
waifu_python/Galleries/PicsRe.py
waifu_python/Galleries/PurrBot.py
waifu_python/Galleries/Rule34.py
waifu_python/Galleries/Sankaku.py
waifu_python/Galleries/WaifuIM.py
waifu_python/Galleries/WaifuPics.py
waifu_python/Galleries/YandeRe.py
waifu_python/Galleries/Zerochan.py
waifu_python/Galleries/__init__.py
waifu_python/Misc/__init__.py
waifu_python/Misc/iwara.py
waifu_python/Pixiv/Pixiv.py
waifu_python/Pixiv/__init__.py
waifu_python/Random/Random.py
waifu_python/Random/__init__.py
waifu_python/Utils/__init__.py
waifu_python/Utils/stdout.py
waifu_python-1.9.4.dist-info/licenses/LICENSE
waifu_python-1.9.4.dist-info/METADATA
waifu_python-1.9.4.dist-info/WHEEL
waifu_python-1.9.4.dist-info/entry_points.txt
waifu_python-1.9.4.dist-info/top_level.txt
waifu_python-1.9.4.dist-info/RECORD
