Metadata-Version: 2.4
Name: waifu-python
Version: 1.9.4
Summary: A project born out of boredom, designed to simplify and reduce the code related to the Waifu API.
Home-page: https://github.com/MisfiT2020/Waifu-Python
Author: Misfit
License: MIT
License-File: LICENSE
Requires-Dist: httpx
Requires-Dist: gallery-dl
Requires-Dist: httpx_socks
Requires-Dist: python-dotenv
Dynamic: author
Dynamic: description
Dynamic: description-content-type
Dynamic: home-page
Dynamic: license
Dynamic: license-file
Dynamic: requires-dist
Dynamic: summary
